mirs_distribution_package/Binomialdistribution.py
mirs_distribution_package/Gaussiandistribution.py
mirs_distribution_package/Generaldistribution.py
mirs_distribution_package/__init__.py
mirs_distribution_package-1.0.dist-info/METADATA
mirs_distribution_package-1.0.dist-info/WHEEL
mirs_distribution_package-1.0.dist-info/top_level.txt
mirs_distribution_package-1.0.dist-info/RECORD
