Metadata-Version: 2.1
Name: mirs-distribution-package
Version: 1.0
Summary: Gaussian mirs_distribution_package
Home-page: UNKNOWN
Author: UNKNOWN
Author-email: UNKNOWN
License: UNKNOWN
Platform: UNKNOWN
